bworker.py
bworker-1.0.0.dist-info/METADATA
bworker-1.0.0.dist-info/WHEEL
bworker-1.0.0.dist-info/entry_points.txt
bworker-1.0.0.dist-info/top_level.txt
bworker-1.0.0.dist-info/RECORD
