Metadata-Version: 2.4
Name: bworker
Version: 1.0.0
Author-email: Piotr Sydow <sydow@wp.pl>
License: MIT
Classifier: Programming Language :: Python :: 3
Classifier: License :: OSI Approved :: MIT License
Classifier: Operating System :: OS Independent
Requires-Python: >=3.6
Requires-Dist: docopt>=0.6.2
Requires-Dist: mako>=1.1.6
